api_project_generator/__init__.py
api_project_generator/application.py
api_project_generator/commands/__init__.py
api_project_generator/commands/_create_api.py
api_project_generator/commands/_create_dto.py
api_project_generator/commands/_create_entity.py
api_project_generator/commands/_create_enum.py
api_project_generator/commands/_create_table.py
api_project_generator/commands/_update_imports.py
api_project_generator/helpers/__init__.py
api_project_generator/helpers/dependencies.py
api_project_generator/helpers/files.py
api_project_generator/helpers/functions.py
api_project_generator/helpers/git_repo.py
api_project_generator/helpers/module_file.py
api_project_generator/helpers/module_helper.py
api_project_generator/helpers/repository.py
api_project_generator/helpers/request.py
api_project_generator/helpers/strings.py
api_project_generator/main.py
api_project_generator/models/__init__.py
api_project_generator/models/project_info.py
api_project_generator/models/pyproject_toml.py
api_project_generator-0.6.0.dist-info/entry_points.txt
api_project_generator-0.6.0.dist-info/LICENSE
api_project_generator-0.6.0.dist-info/WHEEL
api_project_generator-0.6.0.dist-info/METADATA
api_project_generator-0.6.0.dist-info/RECORD
