Metadata-Version: 2.1
Name: api-project-generator
Version: 0.6.0
Summary: 
Author: Gustavo Correa
Author-email: self.gustavocorrea@gmail.com
Requires-Python: >=3.9,<4.0
Classifier: Programming Language :: Python :: 3
Classifier: Programming Language :: Python :: 3.9
Requires-Dist: GitPython (>=3.1.18,<4.0.0)
Requires-Dist: typer (>=0.3.2,<0.4.0)
